[
  { "shortcut": "ctrl + a - ", "description": "Select all" },
  { "shortcut": "ctrl + b - ", "description": "Bold" },
  { "shortcut": "ctrl + c - ", "description": "Copy" },
  { "shortcut": "ctrl + d - ", "description": "Size style/font" },
  { "shortcut": "ctrl + e - ", "description": "Centre align" },
  { "shortcut": "ctrl + f - ", "description": "Find" },
  { "shortcut": "ctrl + g - ", "description": "Go to" },
  { "shortcut": "ctrl + h - ", "description": "Replace" },
  { "shortcut": "ctrl + i - ", "description": "Italic" },
  { "shortcut": "ctrl + j - ", "description": "Justify align/gap" },
  { "shortcut": "ctrl + k - ", "description": "Insert hyperlink" },
  { "shortcut": "ctrl + l - ", "description": "Left align" },
  { "shortcut": "ctrl + m - ", "description": "Move right" },
  { "shortcut": "ctrl + n - ", "description": "New blank page" },
  { "shortcut": "ctrl + o - ", "description": "Open" },
  { "shortcut": "ctrl + p - ", "description": "Print" },
  { "shortcut": "ctrl + q - ", "description": "Reduce gap" },
  { "shortcut": "ctrl + r - ", "description": "Right align" },
  { "shortcut": "ctrl + s - ", "description": "Save" },
  { "shortcut": "ctrl + t - ", "description": "Hanging indent" },
  { "shortcut": "ctrl + u - ", "description": "Underline" },
  { "shortcut": "ctrl + v - ", "description": "Paste" },
  { "shortcut": "ctrl + w - ", "description": "Exit" },
  { "shortcut": "ctrl + x - ", "description": "Cut" },
  { "shortcut": "ctrl + y - ", "description": "Redo" },
  { "shortcut": "ctrl + z - ", "description": "Undo" },
  { "shortcut": "ctrl + F1 - ", "description": "Minimize/maximize the ribbon" },
  { "shortcut": "ctrl + F2 - ", "description": "Print preview command" },
  { "shortcut": "ctrl + F3 - ", "description": "Cut to the spike" },
  { "shortcut": "ctrl + F4 - ", "description": "Close the window" },
  { "shortcut": "ctrl + F5 - ", "description": "Empty" },
  { "shortcut": "ctrl + F6 - ", "description": "Go to the next window" },
  { "shortcut": "ctrl + F7 - ", "description": "Empty" },
  { "shortcut": "ctrl + F8 - ", "description": "Empty" },
  { "shortcut": "ctrl + F9 - ", "description": "Insert an empty field" },
  { "shortcut": "ctrl + F10 - ", "description": "Maximize the document window" },
  { "shortcut": "ctrl + F11 - ", "description": "Lock a field" },
  { "shortcut": "ctrl + F12 - ", "description": "Open command" },
  { "shortcut": "Alt + Tab - ", "description": "Forward scroll through open applications" },
  { "shortcut": "alt + shift + tab - ", "description": "Reverse scroll through open applications" },
  { "shortcut": "F1 - ", "description": "Display help for the current application" },
  { "shortcut": "F2 - ", "description": "Rename highlighted object" },
  { "shortcut": "F4 - ", "description": "Position cursor at the address bar in Windows Explorer" },
  { "shortcut": "F5 - ", "description": "Refresh contents in Internet Explorer" },
  { "shortcut": "F8 (during boot) - ", "description": "Display Windows start and diagnostic menu" },
  { "shortcut": "F10 - ", "description": "Display menu bar options" },
  { "shortcut": "alt + F4 - ", "description": "Close current application" },
  { "shortcut": "ctrl + F4 - ", "description": "Close open window in current application" },
  { "shortcut": "shift + del - ", "description": "Permanently delete items, even from recycle bin" },
  { "shortcut": "Esc - ", "description": "Exit/cancel" },
  { "shortcut": "Backspace - ", "description": "Delete one character to the left" },
  { "shortcut": "Delete - ", "description": "Delete one character to the right" },
  { "shortcut": "Home - ", "description": "Go to beginning of line" },
  { "shortcut": "End - ", "description": "Go to end of line" },
  { "shortcut": "Enter - ", "description": "Insert new paragraph" },
  { "shortcut": "Arrow up - ", "description": "Up one line" },
  { "shortcut": "Arrow down - ", "description": "Down one line" },
  { "shortcut": "Ctrl + Tab - ", "description": "Switch Between Open Tabs" },
  { "shortcut": "Ctrl + Shift + Tab - ", "description": "Switch Between Open Tabs (Reverse)" },
  { "shortcut": "Ctrl + Shift + T - ", "description": "Reopen Closed Tab" },
  { "shortcut": "Alt + Tab - ", "description": "Switch Between Open Applications" },
  { "shortcut": "Alt + F4 - ", "description": "Close Active Window" },
  { "shortcut": "Alt + Space - ", "description": "Open Window Menu" },
  { "shortcut": "Alt + Enter - ", "description": "Open Properties" },
  { "shortcut": "Alt + Esc - ", "description": "Cycle Through Open Windows" },
  { "shortcut": "Win + L - ", "description": "Lock Your PC" },
  { "shortcut": "Win + D - ", "description": "Show Desktop" },
  { "shortcut": "Win + E - ", "description": "Open File Explorer" },
  { "shortcut": "Win + R - ", "description": "Open Run Dialog Box" },
  { "shortcut": "Win + S - ", "description": "Open Search" },
  { "shortcut": "Win + M - ", "description": "Minimize All Windows" },
  { "shortcut": "Win + Shift + M - ", "description": "Restore Minimized Windows" },
  { "shortcut": "Win + Up Arrow - ", "description": "Maximize Window" },
  { "shortcut": "Win + Down Arrow - ", "description": "Minimize Window" },
  { "shortcut": "Win + Left Arrow - ", "description": "Snap Window to Left" },
  { "shortcut": "Win + Right Arrow - ", "description": "Snap Window to Right" },
  { "shortcut": "F1 - ", "description": "Help" },
  { "shortcut": "F2 - ", "description": "Rename" },
  { "shortcut": "F3 - ", "description": "Search" },
  { "shortcut": "F4 - ", "description": "Address Bar" },
  { "shortcut": "F5 - ", "description": "Refresh" },
  { "shortcut": "F11 - ", "description": "Full Screen Mode" },
  { "shortcut": "Shift + Delete - ", "description": "Delete Permanently" },
  { "shortcut": "Ctrl + Shift + Esc - ", "description": "Open Task Manager" },
  { "shortcut": "Ctrl + Shift + N - ", "description": "New Folder" },
  { "shortcut": "Ctrl + Shift + Delete - ", "description": "Clear Browsing Data" },
  { "shortcut": "Ctrl + Shift + S - ", "description": "Save As" },
  { "shortcut": "Ctrl + Shift + P - ", "description": "Print Preview" },
  { "shortcut": "Ctrl + Alt + Delete - ", "description": "Open Security Options" },
  { "shortcut": "Ctrl + Alt + T - ", "description": "Open Terminal" },
  { "shortcut": "Cmd + C - ", "description": "Copy (macOS)" },
  { "shortcut": "Cmd + V - ", "description": "Paste (macOS)" },
  { "shortcut": "Cmd + X - ", "description": "Cut (macOS)" },
  { "shortcut": "Cmd + Z - ", "description": "Undo (macOS)" },
  { "shortcut": "Cmd + Y - ", "description": "Redo (macOS)" },
  { "shortcut": "Cmd + A - ", "description": "Select All (macOS)" },
  { "shortcut": "Cmd + S - ", "description": "Save (macOS)" },
  { "shortcut": "Cmd + P - ", "description": "Print (macOS)" },
  { "shortcut": "Cmd + F - ", "description": "Find (macOS)" },
  { "shortcut": "Cmd + H - ", "description": "Hide (macOS)" },
  { "shortcut": "Cmd + N - ", "description": "New Document (macOS)" },
  { "shortcut": "Cmd + O - ", "description": "Open Document (macOS)" },
  { "shortcut": "Cmd + W - ", "description": "Close Window (macOS)" },
  { "shortcut": "Cmd + T - ", "description": "Open New Tab (macOS)" },
  { "shortcut": "Cmd + L - ", "description": "Focus Address Bar (macOS)" },
  { "shortcut": "Cmd + D - ", "description": "Bookmark Page (macOS)" },
  { "shortcut": "Cmd + Shift + T - ", "description": "Reopen Closed Tab (macOS)" },
  { "shortcut": "Cmd + R - ", "description": "Refresh Page (macOS)" },
  { "shortcut": "Cmd + Q - ", "description": "Quit Application (macOS)" },
  { "shortcut": "Cmd + Space - ", "description": "Spotlight Search (macOS)" },
  { "shortcut": "Cmd + , - ", "description": "Open Preferences (macOS)" },
  { "shortcut": "Cmd + Option + Esc - ", "description": "Force Quit (macOS)" },
  { "shortcut": "Cmd + Shift + 3 - ", "description": "Screenshot (macOS)" },
  { "shortcut": "Cmd + Shift + 4 - ", "description": "Screenshot (macOS)" },
  { "shortcut": "Cmd + Shift + 5 - ", "description": "Screenshot (macOS)" }
]
